aind_metadata_service_async_client/__init__.py
aind_metadata_service_async_client/api_client.py
aind_metadata_service_async_client/api_response.py
aind_metadata_service_async_client/configuration.py
aind_metadata_service_async_client/exceptions.py
aind_metadata_service_async_client/py.typed
aind_metadata_service_async_client/rest.py
aind_metadata_service_async_client/api/__init__.py
aind_metadata_service_async_client/api/default_api.py
aind_metadata_service_async_client/api/healthcheck_api.py
aind_metadata_service_async_client/models/__init__.py
aind_metadata_service_async_client/models/health_check.py
aind_metadata_service_async_client/models/http_validation_error.py
aind_metadata_service_async_client/models/slims_workflow.py
aind_metadata_service_async_client/models/validation_error.py
aind_metadata_service_async_client/models/validation_error_loc_inner.py
aind_metadata_service_async_client-2.6.1.dist-info/METADATA
aind_metadata_service_async_client-2.6.1.dist-info/WHEEL
aind_metadata_service_async_client-2.6.1.dist-info/top_level.txt
aind_metadata_service_async_client-2.6.1.dist-info/RECORD
